silverspeak/__init__.py
silverspeak/__main__.py
silverspeak/homoglyphs/__init__.py
silverspeak/homoglyphs/greedy_attack.py
silverspeak/homoglyphs/identical_map.json
silverspeak/homoglyphs/normalize.py
silverspeak/homoglyphs/ocr_chars_map.json
silverspeak/homoglyphs/random_attack.py
silverspeak/homoglyphs/unicode_confusables_map.json
silverspeak/homoglyphs/utils.py
silverspeak/utils.py
silverspeak-2.2.0.dist-info/LICENSE
silverspeak-2.2.0.dist-info/METADATA
silverspeak-2.2.0.dist-info/WHEEL
silverspeak-2.2.0.dist-info/RECORD
