Metadata-Version: 2.3
Name: silverspeak
Version: 2.2.0
Summary: A Python library to perform homoglyph-based attacks on text. It supports both identical and non-identical homoglyphs across multiple languages.
License: GPL-3.0
Keywords: homoglyph,attack,text,security
Author: Aldan Creo
Author-email: os@acmc.fyi
Requires-Python: >=3.9,<4.0
Classifier: License :: OSI Approved :: GNU General Public License v3 (GPLv3)
Classifier: Programming Language :: Python :: 3
Classifier: Programming Language :: Python :: 3.9
Classifier: Programming Language :: Python :: 3.10
Classifier: Programming Language :: Python :: 3.11
Classifier: Programming Language :: Python :: 3.12
Classifier: Programming Language :: Python :: 3.13
Requires-Dist: pandas (==2.2.2)
